SinhalaTools/__init__.py
SinhalaTools/input_tools.py
SinhalaTools/main.py
SinhalaTools/sinhala_matches.py
SinhalaTools/translator.py
SinhalaTools/unicode_convertor.py
SinhalaTools-0.0.7.dist-info/METADATA
SinhalaTools-0.0.7.dist-info/WHEEL
SinhalaTools-0.0.7.dist-info/top_level.txt
SinhalaTools-0.0.7.dist-info/RECORD
