Metadata-Version: 2.1
Name: SinhalaTools
Version: 0.0.7
Summary: Sinhala Tools for converting Sinhala text to Roman and vice versa.
Home-page: https://github.com/TharinduMadhusanka
Author: Tharindu Madhusanka Wimalasena
Author-email: tharindu.20@cse.mrt.ac.lk
Requires-Python: >=3.6
Requires-Dist: requests
